{
	"schemaVersion": 1,
	"id": "horsepiss",
	"version": "${version}",
	"name": "Horse Piss",
	"description": "Introduce a new twist to Minecraft! Obtain the exclusive 'Bucket of Horse Piss' by right-clicking on horses with an empty bucket. Use this unique item to speed up the oxidation of copper blocks, adding a fresh dimension to gameplay.",
	"authors": [
		"buv!"
	],
	"contact": {
		"homepage": "https://fabricmc.net/",
		"sources": "https://github.com/FabricMC/fabric-example-mod"
	},
	"license": "MIT",
	"icon": "assets/horsepiss/icon.png",
	"environment": "*",
	"entrypoints": {
		"main": [
			"acc.buv.horsepiss.HorsePiss"
		],
		"client": [
			"acc.buv.horsepiss.HorsePissClient"
		],
		"fabric-datagen": [
			"acc.buv.horsepiss.HorsePissDataGenerator"
		]
	},
	"mixins": [
		"horsepiss.mixins.json"
	],
	"depends": {
		"fabricloader": ">=0.14.24",
		"minecraft": "~1.20.2",
		"java": ">=17",
		"fabric-api": "*"
	},
	"suggests": {
		"another-mod": "*"
	}
}